{"readme.md":"82ec4441","docs_code_actual-combat_prettier.md":"c4cf41af","index.md":"c68f1f13","docs_ui_index.md":"bbca3378","docs_name_index.md":"b1dd7710","docs_code_actual-combat_stylelint.md":"fe2b2b21","docs_code_actual-combat_eslint.md":"a14cab7b","docs_git_index.md":"44e11183","docs_code_html_index.md":"9d67cbd1","docs_code_js_index.md":"b895de0e","docs_code_ts_index.md":"46e685f9","docs_code_css_index.md":"74d6d1f2","docs_code_vue_index.md":"709e0007","docs_code_actual-combat_git-hooks.md":"3cbabbbe"}
